{
  "user": [
    {
      "name": "Marko",
      "email": "marko@kodego.ph",
      "title": "test",
      "mobile": "1857326529",
      "photo": "https://th.bing.com/th/id/OIP.Iq1QXifXgyi6fmdPBA3bjAHaHa?pid=ImgDet&rs=1",
      "companyName": "kodego",
      "department": "Executive",
      "id": 1
    },
    {
      "name": "Bryan",
      "email": "bry@kodego.ph",
      "title": "test",
      "mobile": "1857326529",
      "photo": "https://th.bing.com/th/id/OIP.Iq1QXifXgyi6fmdPBA3bjAHaHa?pid=ImgDet&rs=1",
      "companyName": "kodego",
      "department": "Executive",
      "id": 2
    }
  ],
  
  "department": [
    {
      "id": "1",
      "departmentName": "Marketing"
    },
    {
      "id": "2",
      "departmentName": "Executive"
    },
    {
      "id": "3",
      "departmentName": "Finance"
    },
    {
      "id": "4",
      "departmentName": "HR"
    },
    {
      "id": "5",
      "departmentName": "ICT"
    }
  ]
}
